{
  "kind": "Document",
  "definitions": [
    {
      "kind": "OperationDefinition",
      "operation": "query",
      "variableDefinitions": [],
      "directives": [],
      "selectionSet": {
        "kind": "SelectionSet",
        "selections": [
          {
            "kind": "Field",
            "name": {
              "kind": "Name",
              "value": "query",
              "loc": {
                "start": 9,
                "end": 14
              }
            },
            "arguments": [],
            "directives": [],
            "selectionSet": {
              "kind": "SelectionSet",
              "selections": [
                {
                  "kind": "Field",
                  "name": {
                    "kind": "Name",
                    "value": "foo",
                    "loc": {
                      "start": 23,
                      "end": 26
                    }
                  },
                  "arguments": [],
                  "directives": [],
                  "selectionSet": {
                    "kind": "SelectionSet",
                    "selections": [
                      {
                        "kind": "Field",
                        "name": {
                          "kind": "Name",
                          "value": "bar",
                          "loc": {
                            "start": 37,
                            "end": 40
                          }
                        },
                        "arguments": [],
                        "directives": [],
                        "selectionSet": {
                          "kind": "SelectionSet",
                          "selections": [
                            {
                              "kind": "Field",
                              "name": {
                                "kind": "Name",
                                "value": "foobar",
                                "loc": {
                                  "start": 53,
                                  "end": 59
                                }
                              },
                              "arguments": [],
                              "directives": [],
                              "loc": {
                                "start": 53,
                                "end": 59
                              }
                            }
                          ],
                          "loc": {
                            "start": 41,
                            "end": 69
                          }
                        },
                        "loc": {
                          "start": 37,
                          "end": 69
                        }
                      }
                    ],
                    "loc": {
                      "start": 27,
                      "end": 77
                    }
                  },
                  "loc": {
                    "start": 23,
                    "end": 77
                  }
                },
                {
                  "kind": "Field",
                  "name": {
                    "kind": "Name",
                    "value": "baz",
                    "loc": {
                      "start": 84,
                      "end": 87
                    }
                  },
                  "arguments": [],
                  "directives": [],
                  "selectionSet": {
                    "kind": "SelectionSet",
                    "selections": [
                      {
                        "kind": "Field",
                        "name": {
                          "kind": "Name",
                          "value": "bar",
                          "loc": {
                            "start": 98,
                            "end": 101
                          }
                        },
                        "arguments": [],
                        "directives": [],
                        "selectionSet": {
                          "kind": "SelectionSet",
                          "selections": [
                            {
                              "kind": "Field",
                              "name": {
                                "kind": "Name",
                                "value": "foobar",
                                "loc": {
                                  "start": 114,
                                  "end": 120
                                }
                              },
                              "arguments": [],
                              "directives": [],
                              "loc": {
                                "start": 114,
                                "end": 120
                              }
                            }
                          ],
                          "loc": {
                            "start": 102,
                            "end": 130
                          }
                        },
                        "loc": {
                          "start": 98,
                          "end": 130
                        }
                      }
                    ],
                    "loc": {
                      "start": 88,
                      "end": 138
                    }
                  },
                  "loc": {
                    "start": 84,
                    "end": 138
                  }
                }
              ],
              "loc": {
                "start": 15,
                "end": 144
              }
            },
            "loc": {
              "start": 9,
              "end": 144
            }
          }
        ],
        "loc": {
          "start": 3,
          "end": 148
        }
      },
      "loc": {
        "start": 3,
        "end": 148
      }
    }
  ],
  "loc": {
    "start": 0,
    "end": 149
  }
}